{"type": "FeatureCollection", "features": [{"type": "Feature", "properties": {"id": 0, "color": ["Grey"], "accentColor": "51583A", "tags": ["outdoor", "tree", "road", "text", "sky", "house", "cloud"], "description": ["outdoor", "road", "grass", "street", "riding", "country", "tree", "sign", "side", "driving", "man", "track", "traffic", "baseball", "fire", "horse"], "captions": ["a sign on the side of a road"], "objects": [], "path": "/Users/denis.murataev/Jyputer_notebooks/comparative_analysis_of_cities/data_two/", "image_name": "stview_0_56.8471428_35.8763934.jpg"}, "geometry": {"type": "Point", "coordinates": [35.8763934, 56.8471428]}}]}