{"type": "FeatureCollection", "features": [{"type": "Feature", "properties": {"id": 0, "color": ["Grey"], "accentColor": "4F5B35", "tags": ["grass", "sky", "outdoor", "road", "cloud", "scene", "tree", "text", "way", "highway", "traveling", "dirt"], "description": ["grass", "outdoor", "road", "scene", "country", "side", "highway", "street", "driving", "traveling", "dirt", "path", "track", "narrow", "train", "truck", "mountain", "sheep", "trail", "cloudy", "motorcycle", "large", "field", "grassy", "riding", "man", "sign", "parked", "herd", "hill", "river", "standing", "people"], "captions": ["a truck traveling down a dirt road"], "objects": ["field"], "path": "/Users/denis.murataev/Jyputer_notebooks/comparative_analysis_of_cities/data_one/", "image_name": "stview_0_54.1976058_37.6627411.jpg"}, "geometry": {"type": "Point", "coordinates": [37.6627411, 54.1976058]}}]}